m3_next/__init__.py
m3_next/actions.py
m3_next/components.py
m3_next/mapper.py
m3_next/results.py
m3_next/static/js/fabric.js
m3_next/static/js/m3-button.js
m3_next/static/js/m3-def.js
m3_next/static/js/m3-desktop.js
m3_next/static/js/m3-grid.js
m3_next/static/js/m3-menuitem.js
m3_next/static/js/q.js
m3_next/static/js/require.js
m3_next-0.5.10.dist-info/METADATA
m3_next-0.5.10.dist-info/WHEEL
m3_next-0.5.10.dist-info/top_level.txt
m3_next-0.5.10.dist-info/RECORD
