Metadata-Version: 2.1
Name: m3-next
Version: 0.5.10
Summary: Генерация интерфейса m3 в виде json-конфигурации ExtJS
Home-page: https://stash.bars-open.ru/projects/BUDG/repos/m3-next
Author: BARS Group
Author-email: bars@bars-open.ru
License: MIT
Platform: UNKNOWN
Classifier: Intended Audience :: Developers
Classifier: Environment :: Web Environment
Classifier: Natural Language :: Russian
Classifier: Natural Language :: English
Classifier: Operating System :: OS Independent
Classifier: Programming Language :: Python
Classifier: License :: OSI Approved :: MIT License
Classifier: Development Status :: 5 - Production/Stable
Requires-Dist: m3-core
Requires-Dist: m3-ui
